LICENSE.txt
README.md
setup.cfg
setup.py
Topsis_Aparna_102016091/__init__.py
Topsis_Aparna_102016091/topsis.py
Topsis_Aparna_102016091.egg-info/PKG-INFO
Topsis_Aparna_102016091.egg-info/SOURCES.txt
Topsis_Aparna_102016091.egg-info/dependency_links.txt
Topsis_Aparna_102016091.egg-info/requires.txt
Topsis_Aparna_102016091.egg-info/top_level.txt